{
  "parent": {
    "type": "NODE",
    "variable": {
      "name": "chaikin",
      "variables": {
        "fast_period": {
          "value": 2,
          "range": {
            "upper": 100,
            "lower": 2
          }
        },
        "slow_period": {
          "value": 88,
          "range": {
            "upper": 100,
            "lower": 2
          }
        },
        "signal_period": {
          "value": 50,
          "range": {
            "upper": 100,
            "lower": 2
          }
        }
      }
    }
  },
  "children": [
    {
      "parent": {
        "type": "NODE",
        "variable": {
          "name": "bop",
          "variables": {
            "buy_threshold": {
              "value": -0.51,
              "range": {
                "upper": 0,
                "lower": -1
              }
            },
            "sell_threshold": {
              "value": 0.17,
              "range": {
                "upper": 1,
                "lower": 0
              }
            },
            "period": {
              "value": 90,
              "range": {
                "upper": 100,
                "lower": 2
              }
            }
          }
        }
      },
      "children": [
        {
          "type": "TERMINAL",
          "variable": "BUY",
          "fixed": false
        },
        {
          "type": "TERMINAL",
          "variable": "HOLD",
          "fixed": false
        },
        {
          "type": "TERMINAL",
          "variable": "SELL",
          "fixed": false
        }
      ]
    },
    {
      "type": "TERMINAL",
      "variable": "BUY",
      "fixed": false
    },
    {
      "type": "TERMINAL",
      "variable": "SELL",
      "fixed": false
    }
  ]
}